{
    "name": "led",
    "translation_fr": "LED",
    "menu": "Base",
    "needing_librairies": null,
    "color": "orange",
    "properties": [
        {
            "name": "Connection",
            "body": [
                {
                    "name": "Pin output",
                    "enter_in": "pin_output",
                    "legal_value": ["3", "4"]
                },
                {
                    "name": "Value",
                    "enter_in": "pin_value",
                    "legal_value": ["HIGH", "LOW"]
                }
            ]
        }
    ],
    "code": [
        {
            "function": "setup",
            "code": "pinMode($pin_output$, OUTPUT);"
        },
        {
            "function": "loop",
            "code": "digitalWrite($pin_output$, pin_value);"
        }
    ]
}